byeprint/__init__.py
byeprint/main.py
byeprint-0.1.1.dist-info/METADATA
byeprint-0.1.1.dist-info/WHEEL
byeprint-0.1.1.dist-info/top_level.txt
byeprint-0.1.1.dist-info/RECORD
