Metadata-Version: 2.2
Name: byeprint
Version: 0.1.1
Summary: Say goodbye to print()
Project-URL: homepage, https://github.com/1qh/byeprint
Project-URL: github, https://github.com/1qh/byeprint
Requires-Dist: executing
Requires-Dist: pygments
Requires-Dist: asttokens
